flask_social_oauth/__init__.py
flask_social_oauth/config.py
flask_social_oauth/handlers.py
flask_social_oauth/helpers.py
flask_social_oauth-1.3.0.dist-info/METADATA
flask_social_oauth-1.3.0.dist-info/WHEEL
flask_social_oauth-1.3.0.dist-info/top_level.txt
flask_social_oauth-1.3.0.dist-info/RECORD
