Metadata-Version: 2.2
Name: flask_social_oauth
Version: 1.3.0
Summary: Flask Social Login is a Python package that simplifies the integration of social login functionality into Flask web applications. With support for popular social authentication providers like Google, GitHub, and Discord, Flask Social Login streamlines the authentication process for users and enables seamless access to your web application.
Author-email: Om Mishra <hello@om-mishra.com>
Project-URL: Homepage, https://docs.om-mishra.com/flask-social-oauth
Project-URL: Issues, https://github.com/om-mishra7/flask-social-oauth/issues
Project-URL: Repository, https://github.com/om-mishra7/flask-social-oauth
Keywords: flask,social,auth,login,oauth,google,github,discord
Requires-Python: >=3.1
Requires-Dist: flask
Requires-Dist: urllib3
Requires-Dist: requests
